odoo10_addon_product_by_supplier-10.0.1.0.0-py2.7-nspkg.pth
odoo/addons/product_by_supplier/__manifest__.py
odoo/addons/product_by_supplier/__init__.py
odoo/addons/product_by_supplier/README.rst
odoo/addons/product_by_supplier/models/__init__.py
odoo/addons/product_by_supplier/models/product_supplierinfo.py
odoo/addons/product_by_supplier/views/product_supplierinfo_view.xml
odoo/addons/product_by_supplier/static/description/index.html
odoo/addons/product_by_supplier/static/description/icon.png
odoo/addons/product_by_supplier/static/images/product_supplier_info.png
odoo10_addon_product_by_supplier-10.0.1.0.0.dist-info/top_level.txt
odoo10_addon_product_by_supplier-10.0.1.0.0.dist-info/WHEEL
odoo10_addon_product_by_supplier-10.0.1.0.0.dist-info/RECORD
odoo10_addon_product_by_supplier-10.0.1.0.0.dist-info/metadata.json
odoo10_addon_product_by_supplier-10.0.1.0.0.dist-info/DESCRIPTION.rst
odoo10_addon_product_by_supplier-10.0.1.0.0.dist-info/METADATA
odoo10_addon_product_by_supplier-10.0.1.0.0.dist-info/namespace_packages.txt
