Metadata-Version: 2.0
Name: odoo10-addon-product-by-supplier
Version: 10.0.1.0.0
Summary: Show products grouped by suppliers
Home-page: http://www.elico-corp.com, 
Author: Elico Corp,Odoo Community Association (OCA)
Author-email: support@odoo-community.org
License: AGPL-3
Platform: UNKNOWN
Requires-Dist: odoo (<10.1dev,>=10.0)
Classifier: Programming Language :: Python :: 2.7
Classifier: Framework :: Odoo
Classifier: License :: OSI Approved :: GNU Affero General Public License v3
